starbot_blindbox/__init__.py
starbot_blindbox/commands/__init__.py
starbot_blindbox/commands/builtin/__init__.py
starbot_blindbox/commands/builtin/data/__init__.py
starbot_blindbox/commands/builtin/data/blindbox_data.py
starbot_blindbox/painter/BlindBoxGenerator.py
starbot_blindbox/painter/__init__.py
starbot_blindbox/utils/__init__.py
starbot_blindbox/utils/mysql.py
starbot_blindbox-1.2.dist-info/METADATA
starbot_blindbox-1.2.dist-info/WHEEL
starbot_blindbox-1.2.dist-info/top_level.txt
starbot_blindbox-1.2.dist-info/RECORD
